Verilog/CLA.v
// Propagate and Generate Block
module progen(
    input Ai, Bi,
    output Gi, Pti, Pi
);
    nor(Pti, Ai, Bi);     // Pti is complement of Ai + Bi
    nand(Gi, Ai, Bi);     // Gi is complement of Ai & Bi
    xor(Pi, Ai, Bi);      // Propagate signal
endmodule

// Intermediate carry calculation
module inter(
    input Gi, Pti, Gi_1, Pti_1,
    output Pij, GPG
);
    wire t1;
    nor(Pij, Pti, Pti_1);         // Pij = (Pti + Pti_1)'
    or(t1, Pti, Gi_1);            // t1 = Pti + Gi_1
    nand(GPG, Gi, t1);            // GPG = (Gi(Pti + Gi_1))'
endmodule

// For C2 and C3 calculation
module AndOr(
    input Pij, GPG, C,
    output Cout
);
    wire t1;
    and(t1, Pij, C);
    or(Cout, GPG, t1);
endmodule

// Main CLA module
module CLA4bit(
    input [3:0] A, B,
    input Cin, clk,     // Added clock input
    output reg [3:0] S, // Changed to registered output
    output reg Cout, Gout, Pout  // Changed to registered outputs
);
    // Add input registers
    reg [3:0] A_reg, B_reg;
    reg Cin_reg;

    // Register inputs
    always @(posedge clk) begin
        A_reg <= A;
        B_reg <= B;
        Cin_reg <= Cin;
    end

    wire [3:0] G, Pt, P;
    wire C1, C2, C3, C4;
    wire Cinbar, P10, P21, P32;
    wire GPG1, GPG2, GPG3;
    wire Puseless, temp1, temp2;
    wire [3:0] Sum_wire;    // Temporary wires for combinational outputs
    wire Cout_wire, Gout_wire, Pout_wire;

    // Generate Cinbar
    not(Cinbar, Cin_reg);

    // Generate P and G for each bit
    progen pg0(A_reg[0], B_reg[0], G[0], Pt[0], P[0]);
    progen pg1(A_reg[1], B_reg[1], G[1], Pt[1], P[1]);
    progen pg2(A_reg[2], B_reg[2], G[2], Pt[2], P[2]);
    progen pg3(A_reg[3], B_reg[3], G[3], Pt[3], P[3]);

    // Intermediate carry calculations
    inter i0(G[0], Pt[0], Cinbar, Pt[0], Puseless, C1);
    inter i1(G[1], Pt[1], G[0], Pt[0], P10, GPG1);
    inter i2(G[2], Pt[2], G[1], Pt[1], P21, GPG2);
    inter i3(G[3], Pt[3], G[2], Pt[2], P32, GPG3);

    // C2 and C3 calculation
    AndOr ao1(P10, GPG1, Cin, C2);
    AndOr ao2(P21, GPG2, C1, C3);

    // Sum calculation
    xor(Sum_wire[0], Cin, P[0]);
    xor(Sum_wire[1], C1, P[1]);
    xor(Sum_wire[2], C2, P[2]);
    xor(Sum_wire[3], C3, P[3]);

    // Gout calculation
    and(temp1, P32, GPG1);
    nor(Gout_wire, temp1, GPG3);

    // Pout calculation
    nand(Pout_wire, P32, P10);

    // Cout calculation
    or(temp2, Pout_wire, Cinbar);
    nand(Cout_wire, temp2, Gout_wire);

    // Register outputs on clock edge
    always @(posedge clk) begin
        S <= Sum_wire;
        Cout <= Cout_wire;
        Gout <= Gout_wire;
        Pout <= Pout_wire;
    end

endmodule

Verilog/CLAtb.v
`timescale 1ns/1ns
`include "CLA.v"

module CLAtb;
    // Test inputs
    reg [3:0] A, B;
    reg Cin;
    reg clk;
    
    // Test outputs
    wire [3:0] S;
    wire Cout, Gout, Pout;
    
    // Instantiate the CLA with clock
    CLA4bit cla_inst(
        .A(A),
        .B(B),
        .Cin(Cin),
        .clk(clk),
        .S(S),
        .Cout(Cout),
        .Gout(Gout),
        .Pout(Pout)
    );

    // Test stimulus with periodic pulses
    initial begin
        $dumpfile("cla_test.vcd");
        $dumpvars(0, CLAtb);

        // Initialize inputs
        A = 4'b0000;
        B = 4'b0000;
        Cin = 0;
        clk = 0;

         #1000;
        $finish;
    end

    // Generate periodic pulses for A bits
    always begin
        #10 A[0] = ~A[0];  // Toggle every 10ns
        #20 A[1] = ~A[1];  // Toggle every 20ns
        #40 A[2] = ~A[2];  // Toggle every 40ns
        #80 A[3] = ~A[3];  // Toggle every 80ns
    end

    // Generate periodic pulses for B bits with different frequencies
    always begin
        #14 B[0] = ~B[0];  // Toggle every 14ns
        #28 B[1] = ~B[1];  // Toggle every 28ns
        #56 B[2] = ~B[2];  // Toggle every 56ns
        #112 B[3] = ~B[3]; // Toggle every 112ns
    end

    // Toggle Cin periodically
    always #160 Cin = ~Cin;  // Toggle every 160ns
    always #5 clk = ~clk;  // 100MHz clock
    
    // Monitor changes
    initial begin
        $monitor($time, " A=%b, B=%b, Cin=%b, S=%b, Cout=%b", A, B, Cin, S, Cout);
    end
endmodule

Verilog/cla_test.vcd
$date
	Mon Nov 18 21:57:40 2024
$end
$version
	Icarus Verilog
$end
$timescale
	1ns
$end
$scope module CLAtb $end
$var wire 4 ! S [3:0] $end
$var wire 1 " Pout $end
$var wire 1 # Gout $end
$var wire 1 $ Cout $end
$var reg 4 % A [3:0] $end
$var reg 4 & B [3:0] $end
$var reg 1 ' Cin $end
$var reg 1 ( clk $end
$scope module cla_inst $end
$var wire 4 ) A [3:0] $end
$var wire 4 * B [3:0] $end
$var wire 1 ' Cin $end
$var wire 1 + Cinbar $end
$var wire 1 , Cout_wire $end
$var wire 1 - Gout_wire $end
$var wire 1 . Pout_wire $end
$var wire 1 ( clk $end
$var wire 1 / temp1 $end
$var wire 1 0 temp2 $end
$var wire 4 1 Sum_wire [3:0] $end
$var wire 1 2 Puseless $end
$var wire 4 3 Pt [3:0] $end
$var wire 1 4 P32 $end
$var wire 1 5 P21 $end
$var wire 1 6 P10 $end
$var wire 4 7 P [3:0] $end
$var wire 1 8 GPG3 $end
$var wire 1 9 GPG2 $end
$var wire 1 : GPG1 $end
$var wire 4 ; G [3:0] $end
$var wire 1 < C3 $end
$var wire 1 = C2 $end
$var wire 1 > C1 $end
$var reg 4 ? A_reg [3:0] $end
$var reg 4 @ B_reg [3:0] $end
$var reg 1 A Cin_reg $end
$var reg 1 $ Cout $end
$var reg 1 # Gout $end
$var reg 1 " Pout $end
$var reg 4 B S [3:0] $end
$scope module ao1 $end
$var wire 1 ' C $end
$var wire 1 = Cout $end
$var wire 1 C t1 $end
$var wire 1 6 Pij $end
$var wire 1 : GPG $end
$upscope $end
$scope module ao2 $end
$var wire 1 < Cout $end
$var wire 1 D t1 $end
$var wire 1 5 Pij $end
$var wire 1 9 GPG $end
$var wire 1 > C $end
$upscope $end
$scope module i0 $end
$var wire 1 > GPG $end
$var wire 1 E Gi $end
$var wire 1 + Gi_1 $end
$var wire 1 2 Pij $end
$var wire 1 F Pti $end
$var wire 1 G Pti_1 $end
$var wire 1 H t1 $end
$upscope $end
$scope module i1 $end
$var wire 1 : GPG $end
$var wire 1 I Gi $end
$var wire 1 J Gi_1 $end
$var wire 1 6 Pij $end
$var wire 1 K Pti $end
$var wire 1 L Pti_1 $end
$var wire 1 M t1 $end
$upscope $end
$scope module i2 $end
$var wire 1 9 GPG $end
$var wire 1 N Gi $end
$var wire 1 O Gi_1 $end
$var wire 1 5 Pij $end
$var wire 1 P Pti $end
$var wire 1 Q Pti_1 $end
$var wire 1 R t1 $end
$upscope $end
$scope module i3 $end
$var wire 1 8 GPG $end
$var wire 1 S Gi $end
$var wire 1 T Gi_1 $end
$var wire 1 4 Pij $end
$var wire 1 U Pti $end
$var wire 1 V Pti_1 $end
$var wire 1 W t1 $end
$upscope $end
$scope module pg0 $end
$var wire 1 X Ai $end
$var wire 1 Y Bi $end
$var wire 1 Z Gi $end
$var wire 1 [ Pi $end
$var wire 1 \ Pti $end
$upscope $end
$scope module pg1 $end
$var wire 1 ] Ai $end
$var wire 1 ^ Bi $end
$var wire 1 _ Gi $end
$var wire 1 ` Pi $end
$var wire 1 a Pti $end
$upscope $end
$scope module pg2 $end
$var wire 1 b Ai $end
$var wire 1 c Bi $end
$var wire 1 d Gi $end
$var wire 1 e Pi $end
$var wire 1 f Pti $end
$upscope $end
$scope module pg3 $end
$var wire 1 g Ai $end
$var wire 1 h Bi $end
$var wire 1 i Gi $end
$var wire 1 j Pi $end
$var wire 1 k Pti $end
$upscope $end
$upscope $end
$upscope $end
$enddefinitions $end
$comment Show the parameter values. $end
$dumpall
$end
#0
$dumpvars
xk
xj
xi
xh
xg
xf
xe
xd
xc
xb
xa
x`
x_
x^
x]
x\
x[
xZ
xY
xX
xW
xV
xU
xT
xS
xR
xQ
xP
xO
xN
xM
xL
xK
xJ
xI
xH
xG
xF
xE
xD
0C
bx B
xA
bx @
bx ?
x>
x=
x<
bx ;
x:
x9
x8
bx 7
x6
x5
x4
bx 3
x2
bx 1
x0
x/
x.
x-
x,
x+
b0 *
b0 )
0(
0'
b0 &
b0 %
x$
x#
x"
bx !
$end
#5
0,
0=
1-
0<
0:
09
1.
0/
08
0D
02
06
1M
b0 1
05
1R
04
1W
0>
1F
1G
1L
1E
1J
1K
1Q
1I
1O
1P
1V
1N
1T
1U
1S
10
1H
1\
1Z
0[
1a
1_
0`
1f
1d
0e
b1111 3
1k
b1111 ;
1i
b0 7
0j
1+
0Y
0^
0c
0h
0X
0]
0b
0g
0A
b0 @
b0 ?
1(
#10
0(
b1 %
b1 )
#14
b1 &
b1 *
#15
b10 1
12
1>
0F
0G
0L
0E
0J
b1110 3
0\
b1110 ;
0Z
1Y
1X
1"
1#
0$
b0 !
b0 B
b1 @
b1 ?
1(
#20
0(
#25
b10 !
b10 B
1(
#30
0(
b11 %
b11 )
#35
1=
1:
16
0M
b100 1
0K
0Q
b1100 3
0a
b10 7
1`
1]
b11 ?
1(
#40
0(
#42
b11 &
b11 *
#45
b110 1
0I
0O
b1100 ;
0_
b0 7
0`
1^
b11 @
b100 !
b100 B
1(
#50
0(
#55
b110 !
b110 B
1(
#60
0(
#65
1(
#70
0(
b111 %
b111 )
#75
1<
1D
19
15
0R
b1010 1
0P
0V
b1000 3
0f
b100 7
1e
1b
b111 ?
1(
#80
0(
#85
b1010 !
b1010 B
1(
#90
0(
#95
1(
#98
b111 &
b111 *
#100
0(
#105
b1110 1
0N
0T
b1000 ;
0d
b0 7
0e
1c
b111 @
1(
#110
0(
#115
b1110 !
b1110 B
1(
#120
0(
#125
1(
#130
0(
#135
1(
#140
0(
#145
1(
#150
0(
b1111 %
b1111 )
#155
1,
0-
0.
1/
18
14
0W
b110 1
0U
b0 3
0k
b1000 7
1j
1g
b1111 ?
1(
#160
b111 1
1C
0(
b1110 %
b1110 )
1'
#165
1M
b110 1
1E
1J
00
0H
b1001 ;
1Z
b1001 7
1[
0+
0X
1A
b1110 ?
0"
0#
1$
b111 !
b111 B
1(
#170
0(
#175
b110 !
b110 B
1(
#180
0(
b1100 %
b1100 )
#185
0/
0:
1R
b100 1
1I
1O
b1011 ;
1_
b1011 7
1`
0]
b1100 ?
1(
#190
0(
#195
b100 !
b100 B
1(
#200
0(
#205
1(
#210
0(
b1111 &
b1111 *
#215
b1100 1
0S
b11 ;
0i
b11 7
0j
1h
b1111 @
1(
#220
0(
b1000 %
b1000 )
#224
b1110 &
b1110 *
#225
0<
0D
0=
10
0>
0C
1.
1H
02
06
09
1W
b111 1
1F
1G
1L
1N
1T
b1 3
1\
0[
b111 ;
1d
b110 7
1e
0Y
0b
b1110 @
b1000 ?
b1100 !
b1100 B
1(
#230
0(
#235
1"
b111 !
b111 B
1(
#240
0(
#245
1(
#250
0(
#252
b1100 &
b1100 *
#255
05
b101 1
1K
1Q
b11 3
1a
b100 7
0`
0^
b1100 @
1(
#260
0(
#265
b101 !
b101 B
1(
#270
0(
#275
1(
#280
0(
#285
1(
#290
0(
#295
1(
#300
0(
b0 %
b0 )
#305
0,
1-
08
b1101 1
1S
b1111 ;
1i
b1100 7
1j
0g
b0 ?
1(
#308
b1000 &
b1000 *
#310
0(
b1 %
b1 )
#315
1>
04
0H
12
b1010 1
1P
1V
0F
0G
0L
1f
0e
b110 3
0\
b1001 7
1[
0c
1X
1#
0$
b1101 !
b1101 B
b1000 @
b1 ?
1(
#320
b1011 1
0(
0'
#325
b1001 1
0>
1H
1+
0A
b1011 !
b1011 B
1(
#330
0(
b11 %
b11 )
#335
16
b1011 1
0K
0Q
b100 3
0a
b1011 7
1`
1]
b1001 !
b1001 B
b11 ?
1(
#340
0(
#345
b1011 !
b1011 B
1(
#350
0(
#355
1(
#360
0(
#365
1(
#370
0(
b111 %
b111 )
#375
0.
15
14
b1111 1
0P
0V
b0 3
0f
b1111 7
1e
1b
b111 ?
1(
#380
0(
#385
0"
b1111 !
b1111 B
1(
#390
0(
#395
1(
#400
0(
#405
1(
#410
0(
#415
1(
#420
0(
b0 &
b0 *
#425
1.
04
b111 1
1U
b1000 3
1k
b111 7
0j
0h
b0 @
1(
#430
0(
#434
b1 &
b1 *
#435
1<
1=
1D
1:
1>
0M
b1000 1
0E
0J
b1110 ;
0Z
b110 7
0[
1Y
1"
b111 !
b111 B
b1 @
1(
#440
0(
#445
b1000 !
b1000 B
1(
#450
0(
b1111 %
b1111 )
#455
1,
0-
0.
1/
14
b0 1
0U
b0 3
0k
b1110 7
1j
1g
b1111 ?
1(
#460
0(
b1110 %
b1110 )
#462
b11 &
b11 *
#465
19
0D
0R
0>
1M
b1 1
0I
0O
1E
1J
0_
0`
b1101 ;
1Z
b1101 7
1[
1^
0X
b11 @
b1110 ?
0"
0#
1$
b0 !
b0 B
1(
#470
0(
#475
b1 !
b1 B
1(
#480
b0 1
1C
0(
b1100 %
b1100 )
1'
#485
1-
0/
09
1D
0:
1R
1>
1I
1O
00
0H
b1111 ;
1_
b1111 7
1`
0+
0]
1A
b1100 ?
b0 !
b0 B
1(
#490
0(
#495
1#
1(
#500
0(
#505
1(
#510
0(
#515
1(
#518
b111 &
b111 *
#520
0(
b1000 %
b1000 )
#525
1c
0b
b111 @
b1000 ?
1(
#530
0(
#535
1(
#540
0(
#545
1(
#550
0(
#555
1(
#560
0(
#565
1(
#570
0(
#575
1(
#580
0(
#585
1(
#590
0(
#595
1(
#600
0(
b0 %
b0 )
#605
0,
10
1.
04
b1000 1
1U
b1000 3
1k
b111 7
0j
0g
b0 ?
1(
#610
0(
b1 %
b1 )
#615
1:
0M
b1001 1
0E
0J
b1110 ;
0Z
b110 7
0[
1X
1"
0$
b1000 !
b1000 B
b1 ?
1(
#620
0(
#625
b1001 !
b1001 B
1(
#630
0(
b11 %
b11 )
b1111 &
b1111 *
#635
1,
00
0-
0.
1/
19
14
0R
b11 1
0U
0I
0O
b0 3
0k
1j
b1100 ;
0_
b1100 7
0`
1h
1]
b1111 @
b11 ?
1(
#640
b10 1
0C
0(
0'
#644
b1110 &
b1110 *
#645
0D
1M
b1 1
0>
1E
1J
10
1H
b1101 ;
1Z
b1101 7
1[
1+
0Y
0A
b1110 @
0"
0#
1$
b10 !
b10 B
1(
#650
0(
#655
b1 !
b1 B
1(
#660
0(
#665
1(
#670
0(
b111 %
b111 )
#672
b1100 &
b1100 *
#675
0=
0/
18
0:
1R
0W
b11 1
1I
1O
0N
0T
1_
1`
b1011 ;
0d
b1011 7
0e
0^
1b
b1100 @
b111 ?
1(
#680
0(
#685
b11 !
b11 B
1(
#690
0(
#695
1(
#700
0(
#705
1(
#710
0(
#715
1(
#720
0(
#725
1(
#728
b1000 &
b1000 *
#730
0(
#735
0,
1-
0<
08
09
1W
b1111 1
1N
1T
b1111 ;
1d
b1111 7
1e
0c
b1000 @
1(
#740
0(
#745
1#
0$
b1111 !
b1111 B
1(
#750
0(
b1111 %
b1111 )
#755
1,
0-
18
b111 1
0S
b111 ;
0i
b111 7
0j
1g
b1111 ?
1(
#760
0(
b1110 %
b1110 )
#765
1.
02
06
b110 1
1F
1G
1L
b1 3
1\
b110 7
0[
0X
b1110 ?
0#
1$
b111 !
b111 B
1(
#770
0(
#775
1"
b110 !
b110 B
1(
#780
0(
b1100 %
b1100 )
#785
05
b100 1
1K
1Q
b11 3
1a
b100 7
0`
0]
b1100 ?
1(
#790
0(
#795
b100 !
b100 B
1(
#800
b101 1
0(
1'
#805
0+
1A
b101 !
b101 B
1(
#810
0(
#815
1(
#820
0(
b1000 %
b1000 )
#825
04
b1 1
1P
1V
b111 3
1f
b0 7
0e
0b
b1000 ?
1(
#830
0(
#835
b1 !
b1 B
1(
#840
0(
b0 &
b0 *
#845
0,
1-
08
b1001 1
1S
b1111 ;
1i
b1000 7
1j
0h
b0 @
1(
#850
0(
#854
b1 &
b1 *
#855
1>
0H
12
b1010 1
0F
0G
0L
b110 3
0\
b1001 7
1[
1Y
1#
0$
b1001 !
b1001 B
b1 @
1(
#860
0(
#865
b1010 !
b1010 B
1(
#870
0(
#875
1(
#880
0(
#882
b11 &
b11 *
#885
1=
1C
16
b1100 1
0K
0Q
b100 3
0a
b1011 7
1`
1^
b11 @
1(
#890
0(
#895
b1100 !
b1100 B
1(
#900
0(
b0 %
b0 )
#905
b100 1
1U
b1100 3
1k
b11 7
0j
0g
b0 ?
1(
#910
0(
b1 %
b1 )
#915
1:
0M
b101 1
0E
0J
b1110 ;
0Z
b10 7
0[
1X
b100 !
b100 B
b1 ?
1(
#920
0(
#925
b101 !
b101 B
1(
#930
0(
b11 %
b11 )
#935
b111 1
0I
0O
b1100 ;
0_
b0 7
0`
1]
b11 ?
1(
#938
b111 &
b111 *
#940
0(
#945
1<
1D
19
15
0R
b1011 1
0P
0V
b1000 3
0f
b100 7
1e
1c
b111 @
b111 !
b111 B
1(
#950
0(
#955
b1011 !
b1011 B
1(
#960
b1010 1
0C
0(
0'
#965
1H
1+
0A
b1010 !
b1010 B
1(
#970
0(
b111 %
b111 )
#975
b1110 1
0N
0T
b1000 ;
0d
b0 7
0e
1b
b111 ?
1(
#980
0(
#985
b1110 !
b1110 B
1(
